eep153_tools/__init__.py
eep153_tools/sheets.py
eep153_tools-0.12.4.dist-info/LICENSE.txt
eep153_tools-0.12.4.dist-info/METADATA
eep153_tools-0.12.4.dist-info/WHEEL
eep153_tools-0.12.4.dist-info/top_level.txt
eep153_tools-0.12.4.dist-info/RECORD
