Metadata-Version: 2.1
Name: eep153-tools
Version: 0.12.4
Summary: Tools used in EEP153
Home-page: https://github.com/ligon/EEP153
Author: Ethan Ligon
Author-email: ligon@berkeley.edu
License: Creative Commons Attribution-Noncommercial-ShareAlike 4.0 International license
License-File: LICENSE.txt
